{
	"12": {
		"9": {},
		"10": {},
		"11": {}
	},
	"02": {
		"11": {},
		"6": {},
		"7": {},
		"12": {},
		"13": {}
	},
	"11": {
		"4": {},
		"2": {},
		"3": {},
		"5": {},
		"8": {}
	},
	"01": {
		"4": {},
		"2": {},
		"3": {},
		"5": {},
		"8": {},
		"13": {}
	},
	"13": {
		"4": {},
		"3": {},
		"2": {},
		"5": {},
		"8": {},
		"9": {},
		"10": {},
		"11": {}
	},
	"03": {
		"6": {},
		"11": {},
		"10": {},
		"5": {},
		"8": {}
	},
	"14": {
		"8": {},
		"9": {},
		"10": {},
		"11": {},
		"6": {},
		"7": {},
		"4": {},
		"12": {}
	},
	"04": {
		"6": {},
		"7": {},
		"10": {},
		"11": {}
	},
	"15": {
		"8": {},
		"9": {},
		"10": {},
		"11": {},
		"6": {},
		"7": {},
		"12": {}
	},
	"05": {
		"11": {},
		"6": {},
		"7": {}
	},
	"00": {
		"11": {},
		"6": {},
		"7": {},
		"12": {},
		"4": {},
		"3": {},
		"2": {},
		"13": {}
	}
}